pypowervm/__init__.py
pypowervm/adapter.py
pypowervm/const.py
pypowervm/entities.py
pypowervm/exceptions.py
pypowervm/i18n.py
pypowervm/log.py
pypowervm/traits.py
pypowervm/util.py
pypowervm/hacking/__init__.py
pypowervm/hacking/checks.py
pypowervm/helpers/__init__.py
pypowervm/helpers/log_helper.py
pypowervm/helpers/sample_helper.py
pypowervm/helpers/vios_busy.py
pypowervm/locale/pypowervm.pot
pypowervm/locale/de/pypowervm.po
pypowervm/locale/es/pypowervm.po
pypowervm/locale/fr/pypowervm.po
pypowervm/locale/it/pypowervm.po
pypowervm/locale/ja/pypowervm.po
pypowervm/locale/ko/pypowervm.po
pypowervm/locale/pt-BR/pypowervm.po
pypowervm/locale/ru/pypowervm.po
pypowervm/locale/zh-Hans/pypowervm.po
pypowervm/locale/zh-Hant/pypowervm.po
pypowervm/tasks/__init__.py
pypowervm/tasks/client_storage.py
pypowervm/tasks/cluster_ssp.py
pypowervm/tasks/cna.py
pypowervm/tasks/ibmi.py
pypowervm/tasks/management_console.py
pypowervm/tasks/master_mode.py
pypowervm/tasks/memory.py
pypowervm/tasks/migration.py
pypowervm/tasks/network_bridger.py
pypowervm/tasks/partition.py
pypowervm/tasks/power.py
pypowervm/tasks/power_opts.py
pypowervm/tasks/scsi_mapper.py
pypowervm/tasks/slot_map.py
pypowervm/tasks/sriov.py
pypowervm/tasks/storage.py
pypowervm/tasks/vfc_mapper.py
pypowervm/tasks/vopt.py
pypowervm/tasks/vterm.py
pypowervm/tasks/hdisk/__init__.py
pypowervm/tasks/hdisk/_fc.py
pypowervm/tasks/hdisk/_iscsi.py
pypowervm/tasks/hdisk/_rbd.py
pypowervm/tasks/monitor/__init__.py
pypowervm/tasks/monitor/host_cpu.py
pypowervm/tasks/monitor/lpar.py
pypowervm/tasks/monitor/util.py
pypowervm/tests/__init__.py
pypowervm/tests/lib.py
pypowervm/tests/test_adapter.py
pypowervm/tests/test_exceptions.py
pypowervm/tests/test_fixtures.py
pypowervm/tests/test_helpers.py
pypowervm/tests/test_i18n.py
pypowervm/tests/test_session.py
pypowervm/tests/test_traits.py
pypowervm/tests/test_util.py
pypowervm/tests/data/cdata.xml
pypowervm-1.1.27.dist-info/DESCRIPTION.rst
pypowervm-1.1.27.dist-info/METADATA
pypowervm-1.1.27.dist-info/RECORD
pypowervm-1.1.27.dist-info/WHEEL
pypowervm-1.1.27.dist-info/metadata.json
pypowervm-1.1.27.dist-info/pbr.json
pypowervm-1.1.27.dist-info/top_level.txt
