Metadata-Version: 2.0
Name: pypowervm
Version: 1.1.27
Summary: Python binding for the PowerVM REST API
Home-page: http://github.com/powervm/
Author: IBM
Author-email: kyleh@us.ibm.com,thorst@us.ibm.com,efried@us.ibm.com,clbush@us.ibm.com
License: UNKNOWN
Platform: UNKNOWN
Classifier: Development Status :: 5 - Production/Stable
Classifier: Intended Audience :: Information Technology
Classifier: Intended Audience :: System Administrators
Classifier: License :: OSI Approved :: Apache Software License
Classifier: Operating System :: POSIX :: Linux
Classifier: Programming Language :: Python
Classifier: Programming Language :: Python :: 3
Classifier: Programming Language :: Python :: 3.6
Requires-Dist: Taskflow (>=3.8.0)
Requires-Dist: babel
Requires-Dist: lxml (!=3.7.0,>=3.4.1)
Requires-Dist: oslo.concurrency (>=3.8.0)
Requires-Dist: oslo.context (>=2.12.0)
Requires-Dist: oslo.i18n (>=2.1.0)
Requires-Dist: oslo.log (>=3.11.0)
Requires-Dist: oslo.utils (>=3.20.0)
Requires-Dist: pbr (>=2.0.0)
Requires-Dist: pyasn1
Requires-Dist: pyasn1-modules
Requires-Dist: pytz (>=2019.3)
Requires-Dist: requests (!=2.12.2,!=2.13.0,>=2.10.0)
Requires-Dist: six (>=1.14.0)
Requires-Dist: futures (>=3.0); (python_version=='3.6')
